[
   {
     "_id": "628664de1046f835fbb6a6a2",
     "index": 0,
     "guid": "421097ea-38cc-4cff-b1e8-6c389e6ddd72",
     "isActive": false,
     "balance": "$3,384.93",
     "picture": "http://placehold.it/32x32",
     "age": 38,
     "eyeColor": "green",
     "name": "Jean Preston",
     "gender": "female",
     "company": "FARMAGE",
     "email": "jeanpreston@farmage.com",
     "phone": "+1 (975) 496-3199",
     "address": "565 Cherry Street, Alderpoint, Missouri, 5504",
     "about": "Id nisi ad ut magna. Lorem duis quis minim enim amet est id dolore proident velit. Excepteur elit commodo est consectetur sunt ipsum irure consectetur elit. Qui esse in ex nisi id deserunt eiusmod. Quis laborum nostrud anim ex.\r\n",
     "registered": "2015-05-12T05:49:06 -06:00",
     "latitude": 44.615542,
     "longitude": -161.119928,
     "tags": [
       "elit",
       "enim",
       "nostrud",
       "voluptate",
       "in",
       "in",
       "labore"
     ],
     "friends": [
       {
         "id": 0,
         "name": "Amanda Cantrell"
       },
       {
         "id": 1,
         "name": "Herman Sweeney"
       },
       {
         "id": 2,
         "name": "Preston Branch"
       }
     ],
     "greeting": "Hello, Jean Preston! You have 9 unread messages.",
     "favoriteFruit": "banana"
   },
   {
     "_id": "628664de9a2f16d0b4170592",
     "index": 1,
     "guid": "c4657a21-7866-4d55-a7ee-257f94518e5f",
     "isActive": true,
     "balance": "$1,900.47",
     "picture": "http://placehold.it/32x32",
     "age": 26,
     "eyeColor": "green",
     "name": "Moody Carver",
     "gender": "male",
     "company": "WATERBABY",
     "email": "moodycarver@waterbaby.com",
     "phone": "+1 (998) 579-2427",
     "address": "978 Dunne Place, Dixie, Federated States Of Micronesia, 7006",
     "about": "Enim deserunt ex anim consectetur ea. Veniam magna sit culpa proident velit nisi amet labore duis mollit sunt. Non incididunt exercitation qui pariatur laboris ex aute in tempor amet enim.\r\n",
     "registered": "2019-11-05T07:43:29 -06:00",
     "latitude": 31.212508,
     "longitude": 53.934233,
     "tags": [
       "veniam",
       "fugiat",
       "ad",
       "qui",
       "officia",
       "ex",
       "amet"
     ],
     "friends": [
       {
         "id": 0,
         "name": "Boyer Potter"
       },
       {
         "id": 1,
         "name": "Bonner Mccray"
       },
       {
         "id": 2,
         "name": "Evelyn Webb"
       }
     ],
     "greeting": "Hello, Moody Carver! You have 10 unread messages.",
     "favoriteFruit": "apple"
   },
   {
     "_id": "628664de4532ecc8fd353f5f",
     "index": 2,
     "guid": "e0f14948-1db3-44b9-ae2d-69ccea086d99",
     "isActive": false,
     "balance": "$2,229.15",
     "picture": "http://placehold.it/32x32",
     "age": 36,
     "eyeColor": "blue",
     "name": "Sabrina Browning",
     "gender": "female",
     "company": "CYTRAK",
     "email": "sabrinabrowning@cytrak.com",
     "phone": "+1 (979) 435-2005",
     "address": "848 Sullivan Place, Clayville, Arizona, 8821",
     "about": "Et proident pariatur aute sint dolor duis reprehenderit quis cupidatat cillum. Excepteur tempor nisi exercitation deserunt. Consectetur amet officia aliqua et aliquip amet amet minim eiusmod. Aliqua exercitation aute reprehenderit ut ex aute dolore nulla. Dolor officia aliquip et minim labore.\r\n",
     "registered": "2021-05-21T04:46:23 -06:00",
     "latitude": -12.50186,
     "longitude": -64.813163,
     "tags": [
       "aliquip",
       "veniam",
       "est",
       "sunt",
       "cillum",
       "eu",
       "sunt"
     ],
     "friends": [
       {
         "id": 0,
         "name": "Bruce Whitfield"
       },
       {
         "id": 1,
         "name": "Vonda Rios"
       },
       {
         "id": 2,
         "name": "Mae Hooper"
       }
     ],
     "greeting": "Hello, Sabrina Browning! You have 5 unread messages.",
     "favoriteFruit": "apple"
   },
   {
     "_id": "628664dea50cbdb0a8685cc7",
     "index": 3,
     "guid": "e7521f3c-6ce8-4c94-8f6f-f288271438ef",
     "isActive": true,
     "balance": "$2,759.63",
     "picture": "http://placehold.it/32x32",
     "age": 28,
     "eyeColor": "blue",
     "name": "Pope Simon",
     "gender": "male",
     "company": "MAGMINA",
     "email": "popesimon@magmina.com",
     "phone": "+1 (956) 504-3599",
     "address": "697 Blake Avenue, Frystown, Oregon, 7062",
     "about": "Adipisicing veniam culpa pariatur occaecat magna laboris labore eiusmod. Fugiat voluptate nisi laborum non. Anim magna est Lorem aliqua aliquip anim sint esse nisi mollit cillum culpa labore. Nulla dolore pariatur est deserunt voluptate deserunt ex et consequat id. Cillum culpa tempor ut fugiat qui magna eiusmod enim nostrud. Eiusmod minim ea aute do consectetur id.\r\n",
     "registered": "2018-07-15T09:18:16 -06:00",
     "latitude": -75.283238,
     "longitude": -10.394745,
     "tags": [
       "id",
       "consequat",
       "in",
       "enim",
       "commodo",
       "veniam",
       "ut"
     ],
     "friends": [
       {
         "id": 0,
         "name": "Anastasia Haney"
       },
       {
         "id": 1,
         "name": "Susie Solis"
       },
       {
         "id": 2,
         "name": "Browning Perez"
       }
     ],
     "greeting": "Hello, Pope Simon! You have 7 unread messages.",
     "favoriteFruit": "apple"
   },
   {
     "_id": "628664de5dfd6dc8ab40a1f1",
     "index": 4,
     "guid": "93eab213-ecec-41a6-b83e-f421caf28580",
     "isActive": true,
     "balance": "$3,438.49",
     "picture": "http://placehold.it/32x32",
     "age": 28,
     "eyeColor": "green",
     "name": "Angelica Kennedy",
     "gender": "female",
     "company": "OZEAN",
     "email": "angelicakennedy@ozean.com",
     "phone": "+1 (949) 507-2538",
     "address": "101 Bushwick Court, Blanco, North Dakota, 3949",
     "about": "Ex ipsum adipisicing aliqua voluptate dolore esse. Non et duis magna ad reprehenderit. Elit nostrud consectetur et ipsum ullamco quis consequat in et non.\r\n",
     "registered": "2017-10-26T06:08:09 -06:00",
     "latitude": 43.007751,
     "longitude": 108.046461,
     "tags": [
       "sunt",
       "amet",
       "consequat",
       "sint",
       "excepteur",
       "elit",
       "sit"
     ],
     "friends": [
       {
         "id": 0,
         "name": "Mills Castillo"
       },
       {
         "id": 1,
         "name": "Cindy Bridges"
       },
       {
         "id": 2,
         "name": "Polly Stafford"
       }
     ],
     "greeting": "Hello, Angelica Kennedy! You have 2 unread messages.",
     "favoriteFruit": "banana"
   },
   {
     "_id": "628664ded2a54c8b524cabd9",
     "index": 5,
     "guid": "c4c9e925-2b3d-41a1-a440-0c0b94904ec5",
     "isActive": true,
     "balance": "$3,101.36",
     "picture": "http://placehold.it/32x32",
     "age": 20,
     "eyeColor": "green",
     "name": "Bonita Henderson",
     "gender": "female",
     "company": "BOVIS",
     "email": "bonitahenderson@bovis.com",
     "phone": "+1 (907) 406-3149",
     "address": "385 Schroeders Avenue, Otranto, Wyoming, 2840",
     "about": "Aute eu ea minim cillum. Veniam quis minim eu irure eiusmod commodo eiusmod nostrud voluptate adipisicing esse deserunt. Et ullamco ut elit cupidatat est qui commodo pariatur laborum anim. Deserunt cillum labore labore nulla enim ad anim amet enim magna ad adipisicing laboris. Consectetur commodo veniam aliqua voluptate adipisicing mollit tempor consectetur veniam consequat fugiat ad id.\r\n",
     "registered": "2015-12-04T03:27:42 -06:00",
     "latitude": 51.46111,
     "longitude": -67.876208,
     "tags": [
       "tempor",
       "ea",
       "cupidatat",
       "commodo",
       "consectetur",
       "ea",
       "aute"
     ],
     "friends": [
       {
         "id": 0,
         "name": "Pennington Holden"
       },
       {
         "id": 1,
         "name": "Day Abbott"
       },
       {
         "id": 2,
         "name": "Agnes Dotson"
       }
     ],
     "greeting": "Hello, Bonita Henderson! You have 7 unread messages.",
     "favoriteFruit": "strawberry"
   }
 ]